emate/__init__.py
emate/hermitian/__init__.py
emate/hermitian/kpm.py
emate/hermitian/cupyops/__init__.py
emate/hermitian/cupyops/kpm.py
emate/hermitian/tfops/__init__.py
emate/hermitian/tfops/kpm.py
emate/linalg/__init__.py
emate/linalg/misc.py
emate/linalg/tfops/__init__.py
emate/linalg/tfops/lanczos.py
emate/symmetric/__init__.py
emate/symmetric/slq.py
emate/symmetric/tfops/__init__.py
emate/symmetric/tfops/slq.py
emate/utils/__init__.py
emate/utils/cupyops/__init__.py
emate/utils/cupyops/kernels.py
emate/utils/cupyops/signal.py
emate/utils/tfops/__init__.py
emate/utils/tfops/kernels.py
emate/utils/tfops/misc.py
emate/utils/tfops/vector_factories.py
emate-1.1.3.dist-info/METADATA
emate-1.1.3.dist-info/WHEEL
emate-1.1.3.dist-info/top_level.txt
emate-1.1.3.dist-info/RECORD
