Metadata-Version: 2.1
Name: emate
Version: 1.1.3
Summary: eMaTe can run in both CPU and GPU and can
Home-page: https://github.com/stdogpkg/emate
Author: Bruno Messias; Thomas K Peron
Author-email: messias.physics@gmail.com
License: MIT
Download-URL: https://github.com/stdogpkg/emate/archive/v1.0.4.tar.gz
Keywords: gpu,science,complex-networks,graphs,matrices,kpm,tensorflow,chebyshev,spectral,eigenvalues
Platform: UNKNOWN
Classifier: Development Status :: 4 - Beta
Classifier: License :: OSI Approved :: MIT License
Classifier: Intended Audience :: Science/Research
Classifier: Programming Language :: Python :: 3
Classifier: Topic :: Scientific/Engineering :: Physics
Classifier: Topic :: Scientific/Engineering :: Mathematics
Classifier: Topic :: Scientific/Engineering :: Information Analysis
Requires-Dist: scipy
Requires-Dist: numpy
Requires-Dist: tensorflow (==1.15.3)
